lxp/__init__.py
lxp/apps.py
lxp/blocks_quiz.py
lxp/decorators.py
lxp/urls.py
lxp/utils.py
lxp/views.py
lxp/wagtail_hooks.py
lxp/blocks/__init__.py
lxp/blocks/cms_blocks.py
lxp/blocks/course_blocks.py
lxp/blocks/topic_blocks.py
lxp/management/__init__.py
lxp/management/commands/__init__.py
lxp/management/commands/migrate2cms.py
lxp/management/commands/migrate_quiz_attempts.py
lxp/migrations/0001_initial.py
lxp/migrations/0002_lxpwebpage.py
lxp/migrations/0003_auto_20220420_1008.py
lxp/migrations/0004_quizattempt_session_key_alter_quizattempt_user.py
lxp/migrations/0005_coursepage_navbar.py
lxp/migrations/0006_alter_academypage_body_alter_activitypage_body_and_more.py
lxp/migrations/0007_delete_lxpsettings.py
lxp/migrations/0008_alter_academypage_body_alter_activitypage_body_and_more.py
lxp/migrations/0009_coursepage_security_group_alter_coursepage_security.py
lxp/migrations/__init__.py
lxp/models/__init__.py
lxp/models/academy.py
lxp/models/activity.py
lxp/models/admin_sidebar.py
lxp/models/course.py
lxp/models/lxp_web_page.py
lxp/models/module.py
lxp/models/quiz.py
lxp/models/quiz_attempt.py
lxp/models/security.py
lxp/models/user_activity.py
lxp/static/lxp/courses/course01.jpg
lxp/static/lxp/courses/course02.jpg
lxp/static/lxp/courses/course03.jpg
lxp/static/lxp/courses/course04.jpg
lxp/static/lxp/css/lxp.css
lxp/static/lxp/css/sidenav.css
lxp/static/lxp/images/activity-icons/activity_completed.svg
lxp/static/lxp/images/activity-icons/default.svg
lxp/static/lxp/images/activity-icons/embedded_media.svg
lxp/static/lxp/images/activity-icons/html.svg
lxp/static/lxp/images/activity-icons/local_page.svg
lxp/static/lxp/images/activity-icons/pdf.svg
lxp/static/lxp/images/activity-icons/plaintext.svg
lxp/static/lxp/images/activity-icons/quiz.svg
lxp/static/lxp/images/activity-icons/quiz_gift.svg
lxp/static/lxp/images/activity-icons/video_vimeo.svg
lxp/static/lxp/images/activity-icons/video_youtube.svg
lxp/static/lxp/images/activity-icons/website.svg
wagtail_lxp-23.8.1.dist-info/LICENSE
wagtail_lxp-23.8.1.dist-info/METADATA
wagtail_lxp-23.8.1.dist-info/WHEEL
wagtail_lxp-23.8.1.dist-info/top_level.txt
wagtail_lxp-23.8.1.dist-info/RECORD
