Metadata-Version: 2.1
Name: wagtail-lxp
Version: 23.8.1
Summary: E-learning platform for Django + Wagtail + CjkCMS.
Home-page: https://github.com/cjkpl/wagtail-lxp
Author: Grzegorz Krol
Author-email: gk@cjk.pl
License: BSD-3-Clause
Classifier: Environment :: Web Environment
Classifier: Framework :: Django
Classifier: Framework :: Django :: 4.0
Classifier: Intended Audience :: Developers
Classifier: License :: OSI Approved :: BSD License
Classifier: Operating System :: OS Independent
Classifier: Programming Language :: Python
Classifier: Programming Language :: Python :: 3
Classifier: Programming Language :: Python :: 3 :: Only
Classifier: Programming Language :: Python :: 3.9
Classifier: Programming Language :: Python :: 3.10
Classifier: Topic :: Internet :: WWW/HTTP
Classifier: Topic :: Internet :: WWW/HTTP :: Site Management
Requires-Python: >=3.9
License-File: LICENSE
Requires-Dist: wagtail-cjkcms >=23.7.1
